{
    "remotePath": "./",
    "host": "10.100.71.130",
    "username": "201501005",
    "password": "201501005",
    "port": 22,
    "secure": false,
    "protocol": "sftp",
    "uploadOnSave": false,
    "passive": false,
    "debug": false,
    "privateKeyPath": null,
    "passphrase": null,
    "agent": null,
    "allow": [],
    "ignore": [
        "\\.vscode",
        "\\.git",
        "\\.DS_Store"
    ],
    "generatedFiles": {
        "extensionsToInclude": [
            ""
        ],
        "path": ""
    }
}